smart_tv_telegram/__init__.py
smart_tv_telegram/__main__.py
smart_tv_telegram/bot.py
smart_tv_telegram/config.py
smart_tv_telegram/devices_collection.py
smart_tv_telegram/http.py
smart_tv_telegram/mtproto.py
smart_tv_telegram/tools.py
smart_tv_telegram/devices/__init__.py
smart_tv_telegram/devices/chromecast_device.py
smart_tv_telegram/devices/device.py
smart_tv_telegram/devices/upnp_device.py
smart_tv_telegram/devices/vlc_device.py
smart_tv_telegram/devices/web_device.py
smart_tv_telegram/devices/xbmc_device.py
smart_tv_telegram/static/index.html
smart_tv_telegram-1.3.9.dev0.dist-info/LICENSE
smart_tv_telegram-1.3.9.dev0.dist-info/METADATA
smart_tv_telegram-1.3.9.dev0.dist-info/WHEEL
smart_tv_telegram-1.3.9.dev0.dist-info/entry_points.txt
smart_tv_telegram-1.3.9.dev0.dist-info/top_level.txt
smart_tv_telegram-1.3.9.dev0.dist-info/RECORD
