Metadata-Version: 2.1
Name: smart_tv_telegram
Version: 1.3.9.dev0
Summary: A Telegram Bot to stream content on your smart TV
Home-page: https://github.com/andrew-ld/smart-tv-telegram
Author: andrew-ld
Author-email: andrew-ld@protonmail.com
Classifier: Programming Language :: Python :: 3
Classifier: License :: OSI Approved :: GNU Affero General Public License v3 or later (AGPLv3+)
Classifier: Operating System :: OS Independent
Requires-Python: >=3.6
License-File: LICENSE
Requires-Dist: aiohttp ==3.8.5
Requires-Dist: aiosignal ==1.3.1
Requires-Dist: async-lru ==2.0.4
Requires-Dist: async-timeout ==4.0.2
Requires-Dist: async-upnp-client ==0.34.1
Requires-Dist: attrs ==23.1.0
Requires-Dist: Brotli ==1.0.9
Requires-Dist: casttube ==0.2.1
Requires-Dist: catt ==0.12.11
Requires-Dist: certifi ==2023.7.22
Requires-Dist: charset-normalizer ==3.2.0
Requires-Dist: click ==8.1.6
Requires-Dist: defusedxml ==0.7.1
Requires-Dist: frozenlist ==1.4.0
Requires-Dist: idna ==3.4
Requires-Dist: ifaddr ==0.2.0
Requires-Dist: multidict ==6.0.4
Requires-Dist: mutagen ==1.46.0
Requires-Dist: protobuf ==4.23.4
Requires-Dist: pyaes ==1.6.1
Requires-Dist: PyChromecast ==13.0.7
Requires-Dist: pycryptodomex ==3.18.0
Requires-Dist: Pyrogram ==2.0.106
Requires-Dist: PySocks ==1.7.1
Requires-Dist: python-didl-lite ==1.3.2
Requires-Dist: requests ==2.31.0
Requires-Dist: TgCrypto ==1.2.5
Requires-Dist: urllib3 ==2.0.4
Requires-Dist: voluptuous ==0.13.1
Requires-Dist: websockets ==11.0.3
Requires-Dist: yarl ==1.9.2
Requires-Dist: yt-dlp ==2023.7.6
Requires-Dist: zeroconf ==0.74.0
